Workbook
Name Slicer_Department: #N/A
Name Slicer_Month: #N/A

Sheet Dashboard
A1: KPI | B1: Value (Lakh)
A2: Total Revenue | B2: ='actual summary'!C17 -> 1278.31
A3: Total Expense | B3: ='actual summary'!B17 -> 614.49
A4: Total Profit | B4: =B2-B3 -> 663.82
A5: Profit % (Margin) | B5: =IF(B2=0,"",B4/B2) -> 0.51929501

Sheet Helper
A1: month | B1: Profit(in lakh)
A2: Apr-2025 | B2: 46.9
A3: May-2025 | B3: 52.73
A4: Jun-2025 | B4: 57.36
A5: Jul-2025 | B5: 49.49
A6: Aug-2025 | B6: 52.23
A7: Sep-2025 | B7: 59.37
A8: Oct-2025 | B8: 64.02
A9: Nov-2025 | B9: 70.1
A10: Dec-2025 | B10: 65.86
A11: Jan-2026 | B11: 44.31
A12: Feb-2026 | B12: 46.74
A13: Mar-2026 | B13: 54.71

Sheet variance
A1: Budget vs Actual variance report
A2: Month | B2: Actual Revenue | C2: Budget Revenue | D2: Var ₹ Rev | E2: Var % Rev | F2: Actual Expense | G2: Budget Expense | H2: Var ₹ Exp | I2: Var % Exp | J2: Actual Profit | K2: Budget Profit | L2: Var ₹ Profit | M2: Var % Profit
A3: Apr-2025 | B3: =INDEX('actual summary'!$C$5:$C$16,MATCH($A3,'actual summary'!$A$5:$A$16,0)) -> 94.52 | C3: =INDEX('budget summary'!$B$5:$B$16,MATCH($A3,'budget summary'!$A$5:$A$16,0)) -> 95 | D3: =B3-C3 -> -0.48 | E3: =IF(C3=0,"",D3/C3) -> -0.0050526316 | F3: =INDEX('actual summary'!$B$5:$B$16,MATCH($A3,'actual summary'!$A$5:$A$16,0)) -> 47.62 | G3: =INDEX('budget summary'!$C$5:$C$16,MATCH($A3,'budget summary'!$A$5:$A$16,0)) -> 48.2 | H3: =F3-G3 -> -0.58 | I3: =IF(G3=0,"",H3/G3) -> -0.012033195 | J3: =INDEX('actual summary'!$E$5:$E$16,MATCH($A3,'actual summary'!$A$5:$A$16,0)) -> 46.9 | K3: =INDEX('budget summary'!$D$5:$D$16,MATCH($A3,'budget summary'!$A$5:$A$16,0)) -> 46.8 | L3: =J3-K3 -> 0.1 | M3: =IF(K3=0,"",L3/K3) -> 0.0021367521
A4: May-2025 | B4: =INDEX('actual summary'!$C$5:$C$16,MATCH($A4,'actual summary'!$A$5:$A$16,0)) -> 104.33 | C4: =INDEX('budget summary'!$B$5:$B$16,MATCH($A4,'budget summary'!$A$5:$A$16,0)) -> 105 | D4: =B4-C4 -> -0.67 | E4: =IF(C4=0,"",D4/C4) -> -0.0063809524 | F4: =INDEX('actual summary'!$B$5:$B$16,MATCH($A4,'actual summary'!$A$5:$A$16,0)) -> 51.6 | G4: =INDEX('budget summary'!$C$5:$C$16,MATCH($A4,'budget summary'!$A$5:$A$16,0)) -> 51 | H4: =F4-G4 -> 0.6 | I4: =IF(G4=0,"",H4/G4) -> 0.011764706 | J4: =INDEX('actual summary'!$E$5:$E$16,MATCH($A4,'actual summary'!$A$5:$A$16,0)) -> 52.73 | K4: =INDEX('budget summary'!$D$5:$D$16,MATCH($A4,'budget summary'!$A$5:$A$16,0)) -> 54 | L4: =J4-K4 -> -1.27 | M4: =IF(K4=0,"",L4/K4) -> -0.023518519
A5: Jun-2025 | B5: =INDEX('actual summary'!$C$5:$C$16,MATCH($A5,'actual summary'!$A$5:$A$16,0)) -> 109.71 | C5: =INDEX('budget summary'!$B$5:$B$16,MATCH($A5,'budget summary'!$A$5:$A$16,0)) -> 110 | D5: =B5-C5 -> -0.29 | E5: =IF(C5=0,"",D5/C5) -> -0.0026363636 | F5: =INDEX('actual summary'!$B$5:$B$16,MATCH($A5,'actual summary'!$A$5:$A$16,0)) -> 52.35 | G5: =INDEX('budget summary'!$C$5:$C$16,MATCH($A5,'budget summary'!$A$5:$A$16,0)) -> 52.4 | H5: =F5-G5 -> -0.05 | I5: =IF(G5=0,"",H5/G5) -> -0.00095419847 | J5: =INDEX('actual summary'!$E$5:$E$16,MATCH($A5,'actual summary'!$A$5:$A$16,0)) -> 57.36 | K5: =INDEX('budget summary'!$D$5:$D$16,MATCH($A5,'budget summary'!$A$5:$A$16,0)) -> 57.6 | L5: =J5-K5 -> -0.24 | M5: =IF(K5=0,"",L5/K5) -> -0.0041666667
A6: Jul-2025 | B6: =INDEX('actual summary'!$C$5:$C$16,MATCH($A6,'actual summary'!$A$5:$A$16,0)) -> 97.25 | C6: =INDEX('budget summary'!$B$5:$B$16,MATCH($A6,'budget summary'!$A$5:$A$16,0)) -> 98 | D6: =B6-C6 -> -0.75 | E6: =IF(C6=0,"",D6/C6) -> -0.0076530612 | F6: =INDEX('actual summary'!$B$5:$B$16,MATCH($A6,'actual summary'!$A$5:$A$16,0)) -> 47.76 | G6: =INDEX('budget summary'!$C$5:$C$16,MATCH($A6,'budget summary'!$A$5:$A$16,0)) -> 47.08 | H6: =F6-G6 -> 0.68 | I6: =IF(G6=0,"",H6/G6) -> 0.0144435 | J6: =INDEX('actual summary'!$E$5:$E$16,MATCH($A6,'actual summary'!$A$5:$A$16,0)) -> 49.49 | K6: =INDEX('budget summary'!$D$5:$D$16,MATCH($A6,'budget summary'!$A$5:$A$16,0)) -> 50.92 | L6: =J6-K6 -> -1.43 | M6: =IF(K6=0,"",L6/K6) -> -0.028083268
A7: Aug-2025 | B7: =INDEX('actual summary'!$C$5:$C$16,MATCH($A7,'actual summary'!$A$5:$A$16,0)) -> 100.57 | C7: =INDEX('budget summary'!$B$5:$B$16,MATCH($A7,'budget summary'!$A$5:$A$16,0)) -> 102 | D7: =B7-C7 -> -1.43 | E7: =IF(C7=0,"",D7/C7) -> -0.014019608 | F7: =INDEX('actual summary'!$B$5:$B$16,MATCH($A7,'actual summary'!$A$5:$A$16,0)) -> 48.34 | G7: =INDEX('budget summary'!$C$5:$C$16,MATCH($A7,'budget summary'!$A$5:$A$16,0)) -> 48.12 | H7: =F7-G7 -> 0.22 | I7: =IF(G7=0,"",H7/G7) -> 0.0045719036 | J7: =INDEX('actual summary'!$E$5:$E$16,MATCH($A7,'actual summary'!$A$5:$A$16,0)) -> 52.23 | K7: =INDEX('budget summary'!$D$5:$D$16,MATCH($A7,'budget summary'!$A$5:$A$16,0)) -> 53.88 | L7: =J7-K7 -> -1.65 | M7: =IF(K7=0,"",L7/K7) -> -0.030623608
A8: Sep-2025 | B8: =INDEX('actual summary'!$C$5:$C$16,MATCH($A8,'actual summary'!$A$5:$A$16,0)) -> 109.46 | C8: =INDEX('budget summary'!$B$5:$B$16,MATCH($A8,'budget summary'!$A$5:$A$16,0)) -> 108 | D8: =B8-C8 -> 1.46 | E8: =IF(C8=0,"",D8/C8) -> 0.013518519 | F8: =INDEX('actual summary'!$B$5:$B$16,MATCH($A8,'actual summary'!$A$5:$A$16,0)) -> 50.09 | G8: =INDEX('budget summary'!$C$5:$C$16,MATCH($A8,'budget summary'!$A$5:$A$16,0)) -> 49.68 | H8: =F8-G8 -> 0.41 | I8: =IF(G8=0,"",H8/G8) -> 0.008252818 | J8: =INDEX('actual summary'!$E$5:$E$16,MATCH($A8,'actual summary'!$A$5:$A$16,0)) -> 59.37 | K8: =INDEX('budget summary'!$D$5:$D$16,MATCH($A8,'budget summary'!$A$5:$A$16,0)) -> 58.32 | L8: =J8-K8 -> 1.05 | M8: =IF(K8=0,"",L8/K8) -> 0.018004115
A9: Oct-2025 | B9: =INDEX('actual summary'!$C$5:$C$16,MATCH($A9,'actual summary'!$A$5:$A$16,0)) -> 126.41 | C9: =INDEX('budget summary'!$B$5:$B$16,MATCH($A9,'budget summary'!$A$5:$A$16,0)) -> 125 | D9: =B9-C9 -> 1.41 | E9: =IF(C9=0,"",D9/C9) -> 0.01128 | F9: =INDEX('actual summary'!$B$5:$B$16,MATCH($A9,'actual summary'!$A$5:$A$16,0)) -> 62.39 | G9: =INDEX('budget summary'!$C$5:$C$16,MATCH($A9,'budget summary'!$A$5:$A$16,0)) -> 62.85 | H9: =F9-G9 -> -0.46 | I9: =IF(G9=0,"",H9/G9) -> -0.0073190135 | J9: =INDEX('actual summary'!$E$5:$E$16,MATCH($A9,'actual summary'!$A$5:$A$16,0)) -> 64.02 | K9: =INDEX('budget summary'!$D$5:$D$16,MATCH($A9,'budget summary'!$A$5:$A$16,0)) -> 62.15 | L9: =J9-K9 -> 1.87 | M9: =IF(K9=0,"",L9/K9) -> 0.030088496
A10: Nov-2025 | B10: =INDEX('actual summary'!$C$5:$C$16,MATCH($A10,'actual summary'!$A$5:$A$16,0)) -> 136.39 | C10: =INDEX('budget summary'!$B$5:$B$16,MATCH($A10,'budget summary'!$A$5:$A$16,0)) -> 135 | D10: =B10-C10 -> 1.39 | E10: =IF(C10=0,"",D10/C10) -> 0.010296296 | F10: =INDEX('actual summary'!$B$5:$B$16,MATCH($A10,'actual summary'!$A$5:$A$16,0)) -> 66.29 | G10: =INDEX('budget summary'!$C$5:$C$16,MATCH($A10,'budget summary'!$A$5:$A$16,0)) -> 66.15 | H10: =F10-G10 -> 0.14 | I10: =IF(G10=0,"",H10/G10) -> 0.0021164021 | J10: =INDEX('actual summary'!$E$5:$E$16,MATCH($A10,'actual summary'!$A$5:$A$16,0)) -> 70.1 | K10: =INDEX('budget summary'!$D$5:$D$16,MATCH($A10,'budget summary'!$A$5:$A$16,0)) -> 68.85 | L10: =J10-K10 -> 1.25 | M10: =IF(K10=0,"",L10/K10) -> 0.01815541
A11: Dec-2025 | B11: =INDEX('actual summary'!$C$5:$C$16,MATCH($A11,'actual summary'!$A$5:$A$16,0)) -> 117.01 | C11: =INDEX('budget summary'!$B$5:$B$16,MATCH($A11,'budget summary'!$A$5:$A$16,0)) -> 115 | D11: =B11-C11 -> 2.01 | E11: =IF(C11=0,"",D11/C11) -> 0.017478261 | F11: =INDEX('actual summary'!$B$5:$B$16,MATCH($A11,'actual summary'!$A$5:$A$16,0)) -> 51.15 | G11: =INDEX('budget summary'!$C$5:$C$16,MATCH($A11,'budget summary'!$A$5:$A$16,0)) -> 51.5 | H11: =F11-G11 -> -0.35 | I11: =IF(G11=0,"",H11/G11) -> -0.0067961165 | J11: =INDEX('actual summary'!$E$5:$E$16,MATCH($A11,'actual summary'!$A$5:$A$16,0)) -> 65.86 | K11: =INDEX('budget summary'!$D$5:$D$16,MATCH($A11,'budget summary'!$A$5:$A$16,0)) -> 63.5 | L11: =J11-K11 -> 2.36 | M11: =IF(K11=0,"",L11/K11) -> 0.037165354
A12: Jan-2026 | B12: =INDEX('actual summary'!$C$5:$C$16,MATCH($A12,'actual summary'!$A$5:$A$16,0)) -> 89.48 | C12: =INDEX('budget summary'!$B$5:$B$16,MATCH($A12,'budget summary'!$A$5:$A$16,0)) -> 90 | D12: =B12-C12 -> -0.52 | E12: =IF(C12=0,"",D12/C12) -> -0.0057777778 | F12: =INDEX('actual summary'!$B$5:$B$16,MATCH($A12,'actual summary'!$A$5:$A$16,0)) -> 45.17 | G12: =INDEX('budget summary'!$C$5:$C$16,MATCH($A12,'budget summary'!$A$5:$A$16,0)) -> 45 | H12: =F12-G12 -> 0.17 | I12: =IF(G12=0,"",H12/G12) -> 0.0037777778 | J12: =INDEX('actual summary'!$E$5:$E$16,MATCH($A12,'actual summary'!$A$5:$A$16,0)) -> 44.31 | K12: =INDEX('budget summary'!$D$5:$D$16,MATCH($A12,'budget summary'!$A$5:$A$16,0)) -> 45 | L12: =J12-K12 -> -0.69 | M12: =IF(K12=0,"",L12/K12) -> -0.015333333
A13: Feb-2026 | B13: =INDEX('actual summary'!$C$5:$C$16,MATCH($A13,'actual summary'!$A$5:$A$16,0)) -> 91.69 | C13: =INDEX('budget summary'!$B$5:$B$16,MATCH($A13,'budget summary'!$A$5:$A$16,0)) -> 92 | D13: =B13-C13 -> -0.31 | E13: =IF(C13=0,"",D13/C13) -> -0.0033695652 | F13: =INDEX('actual summary'!$B$5:$B$16,MATCH($A13,'actual summary'!$A$5:$A$16,0)) -> 44.95 | G13: =INDEX('budget summary'!$C$5:$C$16,MATCH($A13,'budget summary'!$A$5:$A$16,0)) -> 45.52 | H13: =F13-G13 -> -0.57 | I13: =IF(G13=0,"",H13/G13) -> -0.012521968 | J13: =INDEX('actual summary'!$E$5:$E$16,MATCH($A13,'actual summary'!$A$5:$A$16,0)) -> 46.74 | K13: =INDEX('budget summary'!$D$5:$D$16,MATCH($A13,'budget summary'!$A$5:$A$16,0)) -> 46.48 | L13: =J13-K13 -> 0.26 | M13: =IF(K13=0,"",L13/K13) -> 0.0055938038
A14: Mar-2026 | B14: =INDEX('actual summary'!$C$5:$C$16,MATCH($A14,'actual summary'!$A$5:$A$16,0)) -> 101.49 | C14: =INDEX('budget summary'!$B$5:$B$16,MATCH($A14,'budget summary'!$A$5:$A$16,0)) -> 100 | D14: =B14-C14 -> 1.49 | E14: =IF(C14=0,"",D14/C14) -> 0.0149 | F14: =INDEX('actual summary'!$B$5:$B$16,MATCH($A14,'actual summary'!$A$5:$A$16,0)) -> 46.78 | G14: =INDEX('budget summary'!$C$5:$C$16,MATCH($A14,'budget summary'!$A$5:$A$16,0)) -> 47.6 | H14: =F14-G14 -> -0.82 | I14: =IF(G14=0,"",H14/G14) -> -0.017226891 | J14: =INDEX('actual summary'!$E$5:$E$16,MATCH($A14,'actual summary'!$A$5:$A$16,0)) -> 54.71 | K14: =INDEX('budget summary'!$D$5:$D$16,MATCH($A14,'budget summary'!$A$5:$A$16,0)) -> 52.4 | L14: =J14-K14 -> 2.31 | M14: =IF(K14=0,"",L14/K14) -> 0.044083969

Sheet Dept_Summary
A1: Type | B1: (All)
A3: Row Labels | B3: Sum of Amount_Lakh
A4: HR | B4: 56.4
A5: IT | B5: 37.2
A6: Marketing | B6: 182.6
A7: Operations | B7: 159.43
A8: Sales | B8: 1457.17
A9: Grand Total | B9: 1892.8

Sheet actual summary
A3: Sum of Amount_Lakh | B3: Type | E3: Profit(in lakh)
A4: Month | B4: Expense | C4: Revenue | D4: Total Result
A5: Apr-2025 | B5: 47.62 | C5: 94.52 | D5: 142.14 | E5: =C5-B5 -> 46.9
A6: Aug-2025 | B6: 48.34 | C6: 100.57 | D6: 148.91 | E6: =C6-B6 -> 52.23
A7: Dec-2025 | B7: 51.15 | C7: 117.01 | D7: 168.16 | E7: =C7-B7 -> 65.86
A8: Feb-2026 | B8: 44.95 | C8: 91.69 | D8: 136.64 | E8: =C8-B8 -> 46.74
A9: Jan-2026 | B9: 45.17 | C9: 89.48 | D9: 134.65 | E9: =C9-B9 -> 44.31
A10: Jul-2025 | B10: 47.76 | C10: 97.25 | D10: 145.01 | E10: =C10-B10 -> 49.49
A11: Jun-2025 | B11: 52.35 | C11: 109.71 | D11: 162.06 | E11: =C11-B11 -> 57.36
A12: Mar-2026 | B12: 46.78 | C12: 101.49 | D12: 148.27 | E12: =C12-B12 -> 54.71
A13: May-2025 | B13: 51.6 | C13: 104.33 | D13: 155.93 | E13: =C13-B13 -> 52.73
A14: Nov-2025 | B14: 66.29 | C14: 136.39 | D14: 202.68 | E14: =C14-B14 -> 70.1
A15: Oct-2025 | B15: 62.39 | C15: 126.41 | D15: 188.8 | E15: =C15-B15 -> 64.02
A16: Sep-2025 | B16: 50.09 | C16: 109.46 | D16: 159.55 | E16: =C16-B16 -> 59.37
A17: Total Result | B17: 614.49 | C17: 1278.31 | D17: 1892.8 | E17: =SUM(E5:E16) -> 663.82

Sheet budget summary
B3: Data | D3: Profit(budget)_in lakh
A4: Month | B4: Sum of Budget_Revenue_Lakh | C4: Sum of Budget_Expense_Lakh
A5: Apr-2025 | B5: 95 | C5: 48.2 | D5: =B5-C5 -> 46.8
A6: Aug-2025 | B6: 102 | C6: 48.12 | D6: =B6-C6 -> 53.88
A7: Dec-2025 | B7: 115 | C7: 51.5 | D7: =B7-C7 -> 63.5
A8: Feb-2026 | B8: 92 | C8: 45.52 | D8: =B8-C8 -> 46.48
A9: Jan-2026 | B9: 90 | C9: 45 | D9: =B9-C9 -> 45
A10: Jul-2025 | B10: 98 | C10: 47.08 | D10: =B10-C10 -> 50.92
A11: Jun-2025 | B11: 110 | C11: 52.4 | D11: =B11-C11 -> 57.6
A12: Mar-2026 | B12: 100 | C12: 47.6 | D12: =B12-C12 -> 52.4
A13: May-2025 | B13: 105 | C13: 51 | D13: =B13-C13 -> 54
A14: Nov-2025 | B14: 135 | C14: 66.15 | D14: =B14-C14 -> 68.85
A15: Oct-2025 | B15: 125 | C15: 62.85 | D15: =B15-C15 -> 62.15
A16: Sep-2025 | B16: 108 | C16: 49.68 | D16: =B16-C16 -> 58.32
A17: Total Result | B17: 1275 | C17: 615.1 | D17: =SUM(D5:D16) -> 659.9

Sheet Raw_Data
A1: Date | B1: Month | C1: Department | D1: Type | E1: Category | F1: Amount_Lakh
A2: 2025-04-01 | B2: Apr-2025 | C2: Sales | D2: Revenue | E2: Modern Trade | F2: 43.14
A3: 2025-04-01 | B3: Apr-2025 | C3: Sales | D3: Revenue | E3: General Trade | F3: 36.81
A4: 2025-04-01 | B4: Apr-2025 | C4: Sales | D4: Revenue | E4: E-commerce | F4: 14.57
A5: 2025-04-01 | B5: Apr-2025 | C5: Marketing | D5: Expense | E5: Advertising | F5: 9.95
A6: 2025-04-01 | B6: Apr-2025 | C6: Marketing | D6: Expense | E6: Travel | F6: 0.64
A7: 2025-04-01 | B7: Apr-2025 | C7: Sales | D7: Expense | E7: Trade Discount | F7: 8.76
A8: 2025-04-01 | B8: Apr-2025 | C8: Operations | D8: Expense | E8: Logistics | F8: 4.5
A9: 2025-04-01 | B9: Apr-2025 | C9: Operations | D9: Expense | E9: Utilities | F9: 0.6
A10: 2025-04-01 | B10: Apr-2025 | C10: Operations | D10: Expense | E10: Ops Other | F10: 2.87
A11: 2025-04-01 | B11: Apr-2025 | C11: HR | D11: Expense | E11: Salary | F11: 3.2
A12: 2025-04-01 | B12: Apr-2025 | C12: HR | D12: Expense | E12: Rent | F12: 0.9
A13: 2025-04-01 | B13: Apr-2025 | C13: IT | D13: Expense | E13: Salary | F13: 2.2
... A205: 2026-03-01 | B205: Mar-2026 | C205: HR | D205: Expense | E205: Utilities | F205: 0.6

Sheet Budget
A1: Month | B1: Department | C1: Budget_Revenue_Lakh | D1: Budget_Expense_Lakh
A2: Apr-2025 | B2: Sales | C2: 95 | D2: 0
A3: Apr-2025 | B3: Marketing | C3: 0 | D3: 14
A4: Apr-2025 | B4: Sales | C4: 0 | D4: 14
A5: Apr-2025 | B5: Operations | C5: 0 | D5: 12.4
A6: Apr-2025 | B6: HR | C6: 0 | D6: 4.7
A7: Apr-2025 | B7: IT | C7: 0 | D7: 3.1
A8: May-2025 | B8: Sales | C8: 105 | D8: 0
A9: May-2025 | B9: Marketing | C9: 0 | D9: 15
A10: May-2025 | B10: Sales | C10: 0 | D10: 15
A11: May-2025 | B11: Operations | C11: 0 | D11: 13.2
A12: May-2025 | B12: HR | C12: 0 | D12: 4.7
A13: May-2025 | B13: IT | C13: 0 | D13: 3.1
... A73: Mar-2026 | B73: IT | C73: 0 | D73: 3.1
